chapka/__init__.py
chapka-0.0.1.dist-info/WHEEL
chapka-0.0.1.dist-info/METADATA
chapka-0.0.1.dist-info/RECORD
